[
    {
        "destination": "Hôpital Trois-Chêne",
        "ligne": "1",
        "timestamp": "2016-12-12T05:26:25+0100"
    },
    {
        "destination": "Hôpital Trois-Chêne",
        "ligne": "1",
        "timestamp": "2016-12-12T06:06:25+0100"
    },
    {
        "destination": "Hôpital Trois-Chêne",
        "ligne": "1",
        "timestamp": "2016-12-12T06:32:25+0100"
    },
    {
        "destination": "Hôpital Trois-Chêne",
        "ligne": "1",
        "timestamp": "2016-12-12T06:48:25+0100"
    },
    {
        "destination": "Hôpital Trois-Chêne",
        "ligne": "1",
        "timestamp": "2016-12-12T07:03:25+0100"
    },
    {
        "destination": "Hôpital Trois-Chêne",
        "ligne": "1",
        "timestamp": "2016-12-12T07:18:25+0100"
    },
    {
        "destination": "Hôpital Trois-Chêne",
        "ligne": "1",
        "timestamp": "2016-12-12T07:33:25+0100"
    },
    {
        "destination": "Hôpital Trois-Chêne",
        "ligne": "1",
        "timestamp": "2016-12-12T07:49:25+0100"
    },
    {
        "destination": "Hôpital Trois-Chêne",
        "ligne": "1",
        "timestamp": "2016-12-12T08:04:25+0100"
    },
    {
        "destination": "Hôpital Trois-Chêne",
        "ligne": "1",
        "timestamp": "2016-12-12T08:19:25+0100"
    },
    {
        "destination": "Hôpital Trois-Chêne",
        "ligne": "1",
        "timestamp": "2016-12-12T08:34:25+0100"
    },
    {
        "destination": "Hôpital Trois-Chêne",
        "ligne": "1",
        "timestamp": "2016-12-12T08:49:25+0100"
    },
    {
        "destination": "Hôpital Trois-Chêne",
        "ligne": "1",
        "timestamp": "2016-12-12T09:04:25+0100"
    },
    {
        "destination": "Hôpital Trois-Chêne",
        "ligne": "1",
        "timestamp": "2016-12-12T09:22:25+0100"
    },
    {
        "destination": "Hôpital Trois-Chêne",
        "ligne": "1",
        "timestamp": "2016-12-12T09:42:25+0100"
    },
    {
        "destination": "Hôpital Trois-Chêne",
        "ligne": "1",
        "timestamp": "2016-12-12T10:02:25+0100"
    },
    {
        "destination": "Hôpital Trois-Chêne",
        "ligne": "1",
        "timestamp": "2016-12-12T10:22:25+0100"
    },
    {
        "destination": "Hôpital Trois-Chêne",
        "ligne": "1",
        "timestamp": "2016-12-12T10:42:25+0100"
    },
    {
        "destination": "Hôpital Trois-Chêne",
        "ligne": "1",
        "timestamp": "2016-12-12T11:02:25+0100"
    },
    {
        "destination": "Hôpital Trois-Chêne",
        "ligne": "1",
        "timestamp": "2016-12-12T11:22:25+0100"
    },
    {
        "destination": "Hôpital Trois-Chêne",
        "ligne": "1",
        "timestamp": "2016-12-12T11:42:25+0100"
    },
    {
        "destination": "Hôpital Trois-Chêne",
        "ligne": "1",
        "timestamp": "2016-12-12T12:02:25+0100"
    },
    {
        "destination": "Hôpital Trois-Chêne",
        "ligne": "1",
        "timestamp": "2016-12-12T12:22:25+0100"
    },
    {
        "destination": "Hôpital Trois-Chêne",
        "ligne": "1",
        "timestamp": "2016-12-12T12:42:25+0100"
    },
    {
        "destination": "Hôpital Trois-Chêne",
        "ligne": "1",
        "timestamp": "2016-12-12T13:02:25+0100"
    },
    {
        "destination": "Hôpital Trois-Chêne",
        "ligne": "1",
        "timestamp": "2016-12-12T13:22:25+0100"
    },
    {
        "destination": "Hôpital Trois-Chêne",
        "ligne": "1",
        "timestamp": "2016-12-12T13:42:25+0100"
    },
    {
        "destination": "Hôpital Trois-Chêne",
        "ligne": "1",
        "timestamp": "2016-12-12T14:02:25+0100"
    },
    {
        "destination": "Hôpital Trois-Chêne",
        "ligne": "1",
        "timestamp": "2016-12-12T14:22:25+0100"
    },
    {
        "destination": "Hôpital Trois-Chêne",
        "ligne": "1",
        "timestamp": "2016-12-12T14:42:25+0100"
    },
    {
        "destination": "Hôpital Trois-Chêne",
        "ligne": "1",
        "timestamp": "2016-12-12T15:02:25+0100"
    },
    {
        "destination": "Hôpital Trois-Chêne",
        "ligne": "1",
        "timestamp": "2016-12-12T15:22:25+0100"
    },
    {
        "destination": "Hôpital Trois-Chêne",
        "ligne": "1",
        "timestamp": "2016-12-12T15:42:25+0100"
    },
    {
        "destination": "Hôpital Trois-Chêne",
        "ligne": "1",
        "timestamp": "2016-12-12T15:58:25+0100"
    },
    {
        "destination": "Hôpital Trois-Chêne",
        "ligne": "1",
        "timestamp": "2016-12-12T16:13:25+0100"
    },
    {
        "destination": "Hôpital Trois-Chêne",
        "ligne": "1",
        "timestamp": "2016-12-12T16:29:25+0100"
    },
    {
        "destination": "Hôpital Trois-Chêne",
        "ligne": "1",
        "timestamp": "2016-12-12T16:44:25+0100"
    },
    {
        "destination": "Hôpital Trois-Chêne",
        "ligne": "1",
        "timestamp": "2016-12-12T16:59:25+0100"
    },
    {
        "destination": "Hôpital Trois-Chêne",
        "ligne": "1",
        "timestamp": "2016-12-12T17:15:25+0100"
    },
    {
        "destination": "Hôpital Trois-Chêne",
        "ligne": "1",
        "timestamp": "2016-12-12T17:30:25+0100"
    },
    {
        "destination": "Hôpital Trois-Chêne",
        "ligne": "1",
        "timestamp": "2016-12-12T17:45:25+0100"
    },
    {
        "destination": "Hôpital Trois-Chêne",
        "ligne": "1",
        "timestamp": "2016-12-12T18:00:25+0100"
    },
    {
        "destination": "Hôpital Trois-Chêne",
        "ligne": "1",
        "timestamp": "2016-12-12T18:15:25+0100"
    },
    {
        "destination": "Hôpital Trois-Chêne",
        "ligne": "1",
        "timestamp": "2016-12-12T18:31:25+0100"
    },
    {
        "destination": "Hôpital Trois-Chêne",
        "ligne": "1",
        "timestamp": "2016-12-12T18:45:25+0100"
    },
    {
        "destination": "Hôpital Trois-Chêne",
        "ligne": "1",
        "timestamp": "2016-12-12T19:00:25+0100"
    },
    {
        "destination": "Hôpital Trois-Chêne",
        "ligne": "1",
        "timestamp": "2016-12-12T19:18:25+0100"
    },
    {
        "destination": "Hôpital Trois-Chêne",
        "ligne": "1",
        "timestamp": "2016-12-12T19:37:25+0100"
    },
    {
        "destination": "Hôpital Trois-Chêne",
        "ligne": "1",
        "timestamp": "2016-12-12T20:01:25+0100"
    },
    {
        "destination": "Hôpital Trois-Chêne",
        "ligne": "1",
        "timestamp": "2016-12-12T20:31:25+0100"
    },
    {
        "destination": "Hôpital Trois-Chêne",
        "ligne": "1",
        "timestamp": "2016-12-12T21:01:25+0100"
    },
    {
        "destination": "Hôpital Trois-Chêne",
        "ligne": "1",
        "timestamp": "2016-12-12T21:39:25+0100"
    },
    {
        "destination": "Jar.-Botanique",
        "ligne": "1",
        "timestamp": "2016-12-12T06:16:26+0100"
    },
    {
        "destination": "Jar.-Botanique",
        "ligne": "1",
        "timestamp": "2016-12-12T06:34:26+0100"
    },
    {
        "destination": "Jar.-Botanique",
        "ligne": "1",
        "timestamp": "2016-12-12T06:50:26+0100"
    },
    {
        "destination": "Jar.-Botanique",
        "ligne": "1",
        "timestamp": "2016-12-12T07:04:26+0100"
    },
    {
        "destination": "Jar.-Botanique",
        "ligne": "1",
        "timestamp": "2016-12-12T07:19:26+0100"
    },
    {
        "destination": "Jar.-Botanique",
        "ligne": "1",
        "timestamp": "2016-12-12T07:30:26+0100"
    },
    {
        "destination": "Jar.-Botanique",
        "ligne": "1",
        "timestamp": "2016-12-12T07:40:26+0100"
    },
    {
        "destination": "Jar.-Botanique",
        "ligne": "1",
        "timestamp": "2016-12-12T07:48:26+0100"
    },
    {
        "destination": "Jar.-Botanique",
        "ligne": "1",
        "timestamp": "2016-12-12T07:57:26+0100"
    },
    {
        "destination": "Jar.-Botanique",
        "ligne": "1",
        "timestamp": "2016-12-12T08:05:26+0100"
    },
    {
        "destination": "Jar.-Botanique",
        "ligne": "1",
        "timestamp": "2016-12-12T08:13:26+0100"
    },
    {
        "destination": "Jar.-Botanique",
        "ligne": "1",
        "timestamp": "2016-12-12T08:21:26+0100"
    },
    {
        "destination": "Jar.-Botanique",
        "ligne": "1",
        "timestamp": "2016-12-12T08:29:26+0100"
    },
    {
        "destination": "Jar.-Botanique",
        "ligne": "1",
        "timestamp": "2016-12-12T08:36:26+0100"
    },
    {
        "destination": "Jar.-Botanique",
        "ligne": "1",
        "timestamp": "2016-12-12T08:44:26+0100"
    },
    {
        "destination": "Jar.-Botanique",
        "ligne": "1",
        "timestamp": "2016-12-12T08:51:26+0100"
    },
    {
        "destination": "Jar.-Botanique",
        "ligne": "1",
        "timestamp": "2016-12-12T08:59:26+0100"
    },
    {
        "destination": "Jar.-Botanique",
        "ligne": "1",
        "timestamp": "2016-12-12T09:05:26+0100"
    },
    {
        "destination": "Jar.-Botanique",
        "ligne": "1",
        "timestamp": "2016-12-12T09:12:26+0100"
    },
    {
        "destination": "Jar.-Botanique",
        "ligne": "1",
        "timestamp": "2016-12-12T09:19:26+0100"
    },
    {
        "destination": "Jar.-Botanique",
        "ligne": "1",
        "timestamp": "2016-12-12T09:27:26+0100"
    },
    {
        "destination": "Jar.-Botanique",
        "ligne": "1",
        "timestamp": "2016-12-12T09:35:26+0100"
    },
    {
        "destination": "Jar.-Botanique",
        "ligne": "1",
        "timestamp": "2016-12-12T09:42:26+0100"
    },
    {
        "destination": "Jar.-Botanique",
        "ligne": "1",
        "timestamp": "2016-12-12T09:52:26+0100"
    },
    {
        "destination": "Jar.-Botanique",
        "ligne": "1",
        "timestamp": "2016-12-12T10:01:26+0100"
    },
    {
        "destination": "Jar.-Botanique",
        "ligne": "1",
        "timestamp": "2016-12-12T10:11:26+0100"
    },
    {
        "destination": "Jar.-Botanique",
        "ligne": "1",
        "timestamp": "2016-12-12T10:21:26+0100"
    },
    {
        "destination": "Jar.-Botanique",
        "ligne": "1",
        "timestamp": "2016-12-12T10:31:26+0100"
    },
    {
        "destination": "Jar.-Botanique",
        "ligne": "1",
        "timestamp": "2016-12-12T10:41:26+0100"
    },
    {
        "destination": "Jar.-Botanique",
        "ligne": "1",
        "timestamp": "2016-12-12T10:51:26+0100"
    },
    {
        "destination": "Jar.-Botanique",
        "ligne": "1",
        "timestamp": "2016-12-12T11:01:26+0100"
    },
    {
        "destination": "Jar.-Botanique",
        "ligne": "1",
        "timestamp": "2016-12-12T11:11:26+0100"
    },
    {
        "destination": "Jar.-Botanique",
        "ligne": "1",
        "timestamp": "2016-12-12T11:21:26+0100"
    },
    {
        "destination": "Jar.-Botanique",
        "ligne": "1",
        "timestamp": "2016-12-12T11:32:26+0100"
    },
    {
        "destination": "Jar.-Botanique",
        "ligne": "1",
        "timestamp": "2016-12-12T11:42:26+0100"
    },
    {
        "destination": "Jar.-Botanique",
        "ligne": "1",
        "timestamp": "2016-12-12T11:52:26+0100"
    },
    {
        "destination": "Jar.-Botanique",
        "ligne": "1",
        "timestamp": "2016-12-12T12:02:26+0100"
    },
    {
        "destination": "Jar.-Botanique",
        "ligne": "1",
        "timestamp": "2016-12-12T12:12:26+0100"
    },
    {
        "destination": "Jar.-Botanique",
        "ligne": "1",
        "timestamp": "2016-12-12T12:22:26+0100"
    },
    {
        "destination": "Jar.-Botanique",
        "ligne": "1",
        "timestamp": "2016-12-12T12:32:26+0100"
    },
    {
        "destination": "Jar.-Botanique",
        "ligne": "1",
        "timestamp": "2016-12-12T12:42:26+0100"
    },
    {
        "destination": "Jar.-Botanique",
        "ligne": "1",
        "timestamp": "2016-12-12T12:52:26+0100"
    },
    {
        "destination": "Jar.-Botanique",
        "ligne": "1",
        "timestamp": "2016-12-12T13:01:26+0100"
    },
    {
        "destination": "Jar.-Botanique",
        "ligne": "1",
        "timestamp": "2016-12-12T13:11:26+0100"
    },
    {
        "destination": "Jar.-Botanique",
        "ligne": "1",
        "timestamp": "2016-12-12T13:21:26+0100"
    },
    {
        "destination": "Jar.-Botanique",
        "ligne": "1",
        "timestamp": "2016-12-12T13:32:26+0100"
    },
    {
        "destination": "Jar.-Botanique",
        "ligne": "1",
        "timestamp": "2016-12-12T13:41:26+0100"
    },
    {
        "destination": "Jar.-Botanique",
        "ligne": "1",
        "timestamp": "2016-12-12T13:52:26+0100"
    },
    {
        "destination": "Jar.-Botanique",
        "ligne": "1",
        "timestamp": "2016-12-12T14:01:26+0100"
    },
    {
        "destination": "Jar.-Botanique",
        "ligne": "1",
        "timestamp": "2016-12-12T14:12:26+0100"
    },
    {
        "destination": "Jar.-Botanique",
        "ligne": "1",
        "timestamp": "2016-12-12T14:21:26+0100"
    },
    {
        "destination": "Jar.-Botanique",
        "ligne": "1",
        "timestamp": "2016-12-12T14:32:26+0100"
    },
    {
        "destination": "Jar.-Botanique",
        "ligne": "1",
        "timestamp": "2016-12-12T14:41:26+0100"
    },
    {
        "destination": "Jar.-Botanique",
        "ligne": "1",
        "timestamp": "2016-12-12T14:52:26+0100"
    },
    {
        "destination": "Jar.-Botanique",
        "ligne": "1",
        "timestamp": "2016-12-12T15:01:26+0100"
    },
    {
        "destination": "Jar.-Botanique",
        "ligne": "1",
        "timestamp": "2016-12-12T15:12:26+0100"
    },
    {
        "destination": "Jar.-Botanique",
        "ligne": "1",
        "timestamp": "2016-12-12T15:21:26+0100"
    },
    {
        "destination": "Jar.-Botanique",
        "ligne": "1",
        "timestamp": "2016-12-12T15:32:26+0100"
    },
    {
        "destination": "Jar.-Botanique",
        "ligne": "1",
        "timestamp": "2016-12-12T15:41:26+0100"
    },
    {
        "destination": "Jar.-Botanique",
        "ligne": "1",
        "timestamp": "2016-12-12T15:53:26+0100"
    },
    {
        "destination": "Jar.-Botanique",
        "ligne": "1",
        "timestamp": "2016-12-12T16:01:26+0100"
    },
    {
        "destination": "Jar.-Botanique",
        "ligne": "1",
        "timestamp": "2016-12-12T16:12:26+0100"
    },
    {
        "destination": "Jar.-Botanique",
        "ligne": "1",
        "timestamp": "2016-12-12T16:22:26+0100"
    },
    {
        "destination": "Jar.-Botanique",
        "ligne": "1",
        "timestamp": "2016-12-12T16:33:26+0100"
    },
    {
        "destination": "Jar.-Botanique",
        "ligne": "1",
        "timestamp": "2016-12-12T16:42:26+0100"
    },
    {
        "destination": "Jar.-Botanique",
        "ligne": "1",
        "timestamp": "2016-12-12T16:49:26+0100"
    },
    {
        "destination": "Jar.-Botanique",
        "ligne": "1",
        "timestamp": "2016-12-12T16:57:26+0100"
    },
    {
        "destination": "Jar.-Botanique",
        "ligne": "1",
        "timestamp": "2016-12-12T17:04:26+0100"
    },
    {
        "destination": "Jar.-Botanique",
        "ligne": "1",
        "timestamp": "2016-12-12T17:12:26+0100"
    },
    {
        "destination": "Jar.-Botanique",
        "ligne": "1",
        "timestamp": "2016-12-12T17:19:26+0100"
    },
    {
        "destination": "Jar.-Botanique",
        "ligne": "1",
        "timestamp": "2016-12-12T17:27:26+0100"
    },
    {
        "destination": "Jar.-Botanique",
        "ligne": "1",
        "timestamp": "2016-12-12T17:34:26+0100"
    },
    {
        "destination": "Jar.-Botanique",
        "ligne": "1",
        "timestamp": "2016-12-12T17:42:26+0100"
    },
    {
        "destination": "Jar.-Botanique",
        "ligne": "1",
        "timestamp": "2016-12-12T17:50:26+0100"
    },
    {
        "destination": "Jar.-Botanique",
        "ligne": "1",
        "timestamp": "2016-12-12T17:57:26+0100"
    },
    {
        "destination": "Jar.-Botanique",
        "ligne": "1",
        "timestamp": "2016-12-12T18:05:26+0100"
    },
    {
        "destination": "Jar.-Botanique",
        "ligne": "1",
        "timestamp": "2016-12-12T18:12:26+0100"
    },
    {
        "destination": "Jar.-Botanique",
        "ligne": "1",
        "timestamp": "2016-12-12T18:19:26+0100"
    },
    {
        "destination": "Jar.-Botanique",
        "ligne": "1",
        "timestamp": "2016-12-12T18:27:26+0100"
    },
    {
        "destination": "Jar.-Botanique",
        "ligne": "1",
        "timestamp": "2016-12-12T18:35:26+0100"
    },
    {
        "destination": "Jar.-Botanique",
        "ligne": "1",
        "timestamp": "2016-12-12T18:42:26+0100"
    },
    {
        "destination": "Jar.-Botanique",
        "ligne": "1",
        "timestamp": "2016-12-12T18:50:26+0100"
    },
    {
        "destination": "Jar.-Botanique",
        "ligne": "1",
        "timestamp": "2016-12-12T18:57:26+0100"
    },
    {
        "destination": "Jar.-Botanique",
        "ligne": "1",
        "timestamp": "2016-12-12T19:05:26+0100"
    },
    {
        "destination": "Jar.-Botanique",
        "ligne": "1",
        "timestamp": "2016-12-12T19:13:26+0100"
    },
    {
        "destination": "Jar.-Botanique",
        "ligne": "1",
        "timestamp": "2016-12-12T19:19:26+0100"
    },
    {
        "destination": "Jar.-Botanique",
        "ligne": "1",
        "timestamp": "2016-12-12T19:27:26+0100"
    },
    {
        "destination": "Jar.-Botanique",
        "ligne": "1",
        "timestamp": "2016-12-12T19:34:26+0100"
    },
    {
        "destination": "Jar.-Botanique",
        "ligne": "1",
        "timestamp": "2016-12-12T19:42:26+0100"
    },
    {
        "destination": "Jar.-Botanique",
        "ligne": "1",
        "timestamp": "2016-12-12T19:50:26+0100"
    },
    {
        "destination": "Jar.-Botanique",
        "ligne": "1",
        "timestamp": "2016-12-12T20:00:26+0100"
    },
    {
        "destination": "Jar.-Botanique",
        "ligne": "1",
        "timestamp": "2016-12-12T20:10:26+0100"
    },
    {
        "destination": "Jar.-Botanique",
        "ligne": "1",
        "timestamp": "2016-12-12T20:20:26+0100"
    },
    {
        "destination": "Jar.-Botanique",
        "ligne": "1",
        "timestamp": "2016-12-12T20:34:26+0100"
    },
    {
        "destination": "Jar.-Botanique",
        "ligne": "1",
        "timestamp": "2016-12-12T20:49:26+0100"
    },
    {
        "destination": "Jar.-Botanique",
        "ligne": "1",
        "timestamp": "2016-12-12T21:03:26+0100"
    },
    {
        "destination": "Jar.-Botanique",
        "ligne": "1",
        "timestamp": "2016-12-12T21:18:26+0100"
    },
    {
        "destination": "Jar.-Botanique",
        "ligne": "1",
        "timestamp": "2016-12-12T21:33:26+0100"
    },
    {
        "destination": "Jar.-Botanique",
        "ligne": "1",
        "timestamp": "2016-12-12T21:53:26+0100"
    },
    {
        "destination": "Jar.-Botanique",
        "ligne": "1",
        "timestamp": "2016-12-12T22:12:26+0100"
    },
    {
        "destination": "Jar.-Botanique",
        "ligne": "1",
        "timestamp": "2016-12-12T22:31:26+0100"
    },
    {
        "destination": "Jar.-Botanique",
        "ligne": "1",
        "timestamp": "2016-12-12T22:52:26+0100"
    },
    {
        "destination": "Jar.-Botanique",
        "ligne": "1",
        "timestamp": "2016-12-12T23:12:26+0100"
    },
    {
        "destination": "Jar.-Botanique",
        "ligne": "1",
        "timestamp": "2016-12-12T23:32:26+0100"
    },
    {
        "destination": "Jar.-Botanique",
        "ligne": "1",
        "timestamp": "2016-12-12T23:51:26+0100"
    },
    {
        "destination": "Jar.-Botanique",
        "ligne": "1",
        "timestamp": "2016-12-13T00:11:26+0100"
    },
    {
        "destination": "Jar.-Botanique",
        "ligne": "1",
        "timestamp": "2016-12-13T00:31:26+0100"
    },
    {
        "destination": "Petit-Bel-Air",
        "ligne": "1",
        "timestamp": "2016-12-12T05:06:26+0100"
    },
    {
        "destination": "Petit-Bel-Air",
        "ligne": "1",
        "timestamp": "2016-12-12T05:46:26+0100"
    },
    {
        "destination": "Petit-Bel-Air",
        "ligne": "1",
        "timestamp": "2016-12-12T06:22:26+0100"
    },
    {
        "destination": "Petit-Bel-Air",
        "ligne": "1",
        "timestamp": "2016-12-12T06:41:26+0100"
    },
    {
        "destination": "Petit-Bel-Air",
        "ligne": "1",
        "timestamp": "2016-12-12T06:56:26+0100"
    },
    {
        "destination": "Petit-Bel-Air",
        "ligne": "1",
        "timestamp": "2016-12-12T07:11:26+0100"
    },
    {
        "destination": "Petit-Bel-Air",
        "ligne": "1",
        "timestamp": "2016-12-12T07:26:26+0100"
    },
    {
        "destination": "Petit-Bel-Air",
        "ligne": "1",
        "timestamp": "2016-12-12T07:41:26+0100"
    },
    {
        "destination": "Petit-Bel-Air",
        "ligne": "1",
        "timestamp": "2016-12-12T07:56:26+0100"
    },
    {
        "destination": "Petit-Bel-Air",
        "ligne": "1",
        "timestamp": "2016-12-12T08:12:26+0100"
    },
    {
        "destination": "Petit-Bel-Air",
        "ligne": "1",
        "timestamp": "2016-12-12T08:26:26+0100"
    },
    {
        "destination": "Petit-Bel-Air",
        "ligne": "1",
        "timestamp": "2016-12-12T08:41:26+0100"
    },
    {
        "destination": "Petit-Bel-Air",
        "ligne": "1",
        "timestamp": "2016-12-12T08:56:26+0100"
    },
    {
        "destination": "Petit-Bel-Air",
        "ligne": "1",
        "timestamp": "2016-12-12T09:12:26+0100"
    },
    {
        "destination": "Petit-Bel-Air",
        "ligne": "1",
        "timestamp": "2016-12-12T09:32:26+0100"
    },
    {
        "destination": "Petit-Bel-Air",
        "ligne": "1",
        "timestamp": "2016-12-12T09:52:26+0100"
    },
    {
        "destination": "Petit-Bel-Air",
        "ligne": "1",
        "timestamp": "2016-12-12T10:12:26+0100"
    },
    {
        "destination": "Petit-Bel-Air",
        "ligne": "1",
        "timestamp": "2016-12-12T10:32:26+0100"
    },
    {
        "destination": "Petit-Bel-Air",
        "ligne": "1",
        "timestamp": "2016-12-12T10:52:26+0100"
    },
    {
        "destination": "Petit-Bel-Air",
        "ligne": "1",
        "timestamp": "2016-12-12T11:12:26+0100"
    },
    {
        "destination": "Petit-Bel-Air",
        "ligne": "1",
        "timestamp": "2016-12-12T11:32:26+0100"
    },
    {
        "destination": "Petit-Bel-Air",
        "ligne": "1",
        "timestamp": "2016-12-12T11:52:26+0100"
    },
    {
        "destination": "Petit-Bel-Air",
        "ligne": "1",
        "timestamp": "2016-12-12T12:12:26+0100"
    },
    {
        "destination": "Petit-Bel-Air",
        "ligne": "1",
        "timestamp": "2016-12-12T12:32:26+0100"
    },
    {
        "destination": "Petit-Bel-Air",
        "ligne": "1",
        "timestamp": "2016-12-12T12:52:26+0100"
    },
    {
        "destination": "Petit-Bel-Air",
        "ligne": "1",
        "timestamp": "2016-12-12T13:12:26+0100"
    },
    {
        "destination": "Petit-Bel-Air",
        "ligne": "1",
        "timestamp": "2016-12-12T13:32:26+0100"
    },
    {
        "destination": "Petit-Bel-Air",
        "ligne": "1",
        "timestamp": "2016-12-12T13:52:26+0100"
    },
    {
        "destination": "Petit-Bel-Air",
        "ligne": "1",
        "timestamp": "2016-12-12T14:12:26+0100"
    },
    {
        "destination": "Petit-Bel-Air",
        "ligne": "1",
        "timestamp": "2016-12-12T14:32:26+0100"
    },
    {
        "destination": "Petit-Bel-Air",
        "ligne": "1",
        "timestamp": "2016-12-12T14:52:26+0100"
    },
    {
        "destination": "Petit-Bel-Air",
        "ligne": "1",
        "timestamp": "2016-12-12T15:11:26+0100"
    },
    {
        "destination": "Petit-Bel-Air",
        "ligne": "1",
        "timestamp": "2016-12-12T15:32:26+0100"
    },
    {
        "destination": "Petit-Bel-Air",
        "ligne": "1",
        "timestamp": "2016-12-12T15:51:26+0100"
    },
    {
        "destination": "Petit-Bel-Air",
        "ligne": "1",
        "timestamp": "2016-12-12T16:06:26+0100"
    },
    {
        "destination": "Petit-Bel-Air",
        "ligne": "1",
        "timestamp": "2016-12-12T16:21:26+0100"
    },
    {
        "destination": "Petit-Bel-Air",
        "ligne": "1",
        "timestamp": "2016-12-12T16:36:26+0100"
    },
    {
        "destination": "Petit-Bel-Air",
        "ligne": "1",
        "timestamp": "2016-12-12T16:51:26+0100"
    },
    {
        "destination": "Petit-Bel-Air",
        "ligne": "1",
        "timestamp": "2016-12-12T17:07:26+0100"
    },
    {
        "destination": "Petit-Bel-Air",
        "ligne": "1",
        "timestamp": "2016-12-12T17:22:26+0100"
    },
    {
        "destination": "Petit-Bel-Air",
        "ligne": "1",
        "timestamp": "2016-12-12T17:37:26+0100"
    },
    {
        "destination": "Petit-Bel-Air",
        "ligne": "1",
        "timestamp": "2016-12-12T17:53:26+0100"
    },
    {
        "destination": "Petit-Bel-Air",
        "ligne": "1",
        "timestamp": "2016-12-12T18:08:26+0100"
    },
    {
        "destination": "Petit-Bel-Air",
        "ligne": "1",
        "timestamp": "2016-12-12T18:23:26+0100"
    },
    {
        "destination": "Petit-Bel-Air",
        "ligne": "1",
        "timestamp": "2016-12-12T18:38:26+0100"
    },
    {
        "destination": "Petit-Bel-Air",
        "ligne": "1",
        "timestamp": "2016-12-12T18:52:26+0100"
    },
    {
        "destination": "Petit-Bel-Air",
        "ligne": "1",
        "timestamp": "2016-12-12T19:09:26+0100"
    },
    {
        "destination": "Petit-Bel-Air",
        "ligne": "1",
        "timestamp": "2016-12-12T19:28:26+0100"
    },
    {
        "destination": "Petit-Bel-Air",
        "ligne": "1",
        "timestamp": "2016-12-12T19:48:26+0100"
    },
    {
        "destination": "Petit-Bel-Air",
        "ligne": "1",
        "timestamp": "2016-12-12T20:16:26+0100"
    },
    {
        "destination": "Petit-Bel-Air",
        "ligne": "1",
        "timestamp": "2016-12-12T20:46:26+0100"
    },
    {
        "destination": "Petit-Bel-Air",
        "ligne": "1",
        "timestamp": "2016-12-12T21:19:26+0100"
    },
    {
        "destination": "Petit-Bel-Air",
        "ligne": "1",
        "timestamp": "2016-12-12T21:59:26+0100"
    },
    {
        "destination": "Petit-Bel-Air",
        "ligne": "1",
        "timestamp": "2016-12-12T22:19:26+0100"
    },
    {
        "destination": "Petit-Bel-Air",
        "ligne": "1",
        "timestamp": "2016-12-12T22:38:26+0100"
    },
    {
        "destination": "Petit-Bel-Air",
        "ligne": "1",
        "timestamp": "2016-12-12T22:58:26+0100"
    },
    {
        "destination": "Petit-Bel-Air",
        "ligne": "1",
        "timestamp": "2016-12-12T23:18:26+0100"
    },
    {
        "destination": "Petit-Bel-Air",
        "ligne": "1",
        "timestamp": "2016-12-12T23:38:26+0100"
    },
    {
        "destination": "Petit-Bel-Air",
        "ligne": "1",
        "timestamp": "2016-12-12T23:58:26+0100"
    },
    {
        "destination": "Petit-Bel-Air",
        "ligne": "1",
        "timestamp": "2016-12-13T00:18:26+0100"
    },
    {
        "destination": "Jar.-Botanique",
        "ligne": "25",
        "timestamp": "2016-12-12T05:24:26+0100"
    },
    {
        "destination": "Jar.-Botanique",
        "ligne": "25",
        "timestamp": "2016-12-12T05:44:26+0100"
    },
    {
        "destination": "Jar.-Botanique",
        "ligne": "25",
        "timestamp": "2016-12-12T06:05:26+0100"
    },
    {
        "destination": "Jar.-Botanique",
        "ligne": "25",
        "timestamp": "2016-12-12T06:26:26+0100"
    },
    {
        "destination": "Jar.-Botanique",
        "ligne": "25",
        "timestamp": "2016-12-12T06:42:26+0100"
    },
    {
        "destination": "Jar.-Botanique",
        "ligne": "25",
        "timestamp": "2016-12-12T06:57:26+0100"
    },
    {
        "destination": "Jar.-Botanique",
        "ligne": "25",
        "timestamp": "2016-12-12T07:12:26+0100"
    },
    {
        "destination": "Jar.-Botanique",
        "ligne": "25",
        "timestamp": "2016-12-12T07:21:26+0100"
    },
    {
        "destination": "Jar.-Botanique",
        "ligne": "25",
        "timestamp": "2016-12-12T07:28:26+0100"
    },
    {
        "destination": "Jar.-Botanique",
        "ligne": "25",
        "timestamp": "2016-12-12T07:37:26+0100"
    },
    {
        "destination": "Jar.-Botanique",
        "ligne": "25",
        "timestamp": "2016-12-12T07:44:26+0100"
    },
    {
        "destination": "Jar.-Botanique",
        "ligne": "25",
        "timestamp": "2016-12-12T07:53:26+0100"
    },
    {
        "destination": "Jar.-Botanique",
        "ligne": "25",
        "timestamp": "2016-12-12T08:01:26+0100"
    },
    {
        "destination": "Jar.-Botanique",
        "ligne": "25",
        "timestamp": "2016-12-12T08:09:26+0100"
    },
    {
        "destination": "Jar.-Botanique",
        "ligne": "25",
        "timestamp": "2016-12-12T08:17:26+0100"
    },
    {
        "destination": "Jar.-Botanique",
        "ligne": "25",
        "timestamp": "2016-12-12T08:25:26+0100"
    },
    {
        "destination": "Jar.-Botanique",
        "ligne": "25",
        "timestamp": "2016-12-12T08:33:26+0100"
    },
    {
        "destination": "Jar.-Botanique",
        "ligne": "25",
        "timestamp": "2016-12-12T08:40:26+0100"
    },
    {
        "destination": "Jar.-Botanique",
        "ligne": "25",
        "timestamp": "2016-12-12T08:47:26+0100"
    },
    {
        "destination": "Jar.-Botanique",
        "ligne": "25",
        "timestamp": "2016-12-12T08:55:26+0100"
    },
    {
        "destination": "Jar.-Botanique",
        "ligne": "25",
        "timestamp": "2016-12-12T09:02:26+0100"
    },
    {
        "destination": "Jar.-Botanique",
        "ligne": "25",
        "timestamp": "2016-12-12T09:09:26+0100"
    },
    {
        "destination": "Jar.-Botanique",
        "ligne": "25",
        "timestamp": "2016-12-12T09:16:26+0100"
    },
    {
        "destination": "Jar.-Botanique",
        "ligne": "25",
        "timestamp": "2016-12-12T09:23:26+0100"
    },
    {
        "destination": "Jar.-Botanique",
        "ligne": "25",
        "timestamp": "2016-12-12T09:31:26+0100"
    },
    {
        "destination": "Jar.-Botanique",
        "ligne": "25",
        "timestamp": "2016-12-12T09:38:26+0100"
    },
    {
        "destination": "Jar.-Botanique",
        "ligne": "25",
        "timestamp": "2016-12-12T09:47:26+0100"
    },
    {
        "destination": "Jar.-Botanique",
        "ligne": "25",
        "timestamp": "2016-12-12T09:57:26+0100"
    },
    {
        "destination": "Jar.-Botanique",
        "ligne": "25",
        "timestamp": "2016-12-12T10:07:26+0100"
    },
    {
        "destination": "Jar.-Botanique",
        "ligne": "25",
        "timestamp": "2016-12-12T10:16:26+0100"
    },
    {
        "destination": "Jar.-Botanique",
        "ligne": "25",
        "timestamp": "2016-12-12T10:26:26+0100"
    },
    {
        "destination": "Jar.-Botanique",
        "ligne": "25",
        "timestamp": "2016-12-12T10:36:26+0100"
    },
    {
        "destination": "Jar.-Botanique",
        "ligne": "25",
        "timestamp": "2016-12-12T10:46:26+0100"
    },
    {
        "destination": "Jar.-Botanique",
        "ligne": "25",
        "timestamp": "2016-12-12T10:56:26+0100"
    },
    {
        "destination": "Jar.-Botanique",
        "ligne": "25",
        "timestamp": "2016-12-12T11:06:26+0100"
    },
    {
        "destination": "Jar.-Botanique",
        "ligne": "25",
        "timestamp": "2016-12-12T11:16:26+0100"
    },
    {
        "destination": "Jar.-Botanique",
        "ligne": "25",
        "timestamp": "2016-12-12T11:26:26+0100"
    },
    {
        "destination": "Jar.-Botanique",
        "ligne": "25",
        "timestamp": "2016-12-12T11:37:26+0100"
    },
    {
        "destination": "Jar.-Botanique",
        "ligne": "25",
        "timestamp": "2016-12-12T11:47:26+0100"
    },
    {
        "destination": "Jar.-Botanique",
        "ligne": "25",
        "timestamp": "2016-12-12T11:57:26+0100"
    },
    {
        "destination": "Jar.-Botanique",
        "ligne": "25",
        "timestamp": "2016-12-12T12:07:26+0100"
    },
    {
        "destination": "Jar.-Botanique",
        "ligne": "25",
        "timestamp": "2016-12-12T12:16:26+0100"
    },
    {
        "destination": "Jar.-Botanique",
        "ligne": "25",
        "timestamp": "2016-12-12T12:26:26+0100"
    },
    {
        "destination": "Jar.-Botanique",
        "ligne": "25",
        "timestamp": "2016-12-12T12:36:26+0100"
    },
    {
        "destination": "Jar.-Botanique",
        "ligne": "25",
        "timestamp": "2016-12-12T12:46:26+0100"
    },
    {
        "destination": "Jar.-Botanique",
        "ligne": "25",
        "timestamp": "2016-12-12T12:56:26+0100"
    },
    {
        "destination": "Jar.-Botanique",
        "ligne": "25",
        "timestamp": "2016-12-12T13:06:26+0100"
    },
    {
        "destination": "Jar.-Botanique",
        "ligne": "25",
        "timestamp": "2016-12-12T13:16:26+0100"
    },
    {
        "destination": "Jar.-Botanique",
        "ligne": "25",
        "timestamp": "2016-12-12T13:26:26+0100"
    },
    {
        "destination": "Jar.-Botanique",
        "ligne": "25",
        "timestamp": "2016-12-12T13:36:26+0100"
    },
    {
        "destination": "Jar.-Botanique",
        "ligne": "25",
        "timestamp": "2016-12-12T13:46:26+0100"
    },
    {
        "destination": "Jar.-Botanique",
        "ligne": "25",
        "timestamp": "2016-12-12T13:56:26+0100"
    },
    {
        "destination": "Jar.-Botanique",
        "ligne": "25",
        "timestamp": "2016-12-12T14:06:26+0100"
    },
    {
        "destination": "Jar.-Botanique",
        "ligne": "25",
        "timestamp": "2016-12-12T14:16:26+0100"
    },
    {
        "destination": "Jar.-Botanique",
        "ligne": "25",
        "timestamp": "2016-12-12T14:26:26+0100"
    },
    {
        "destination": "Jar.-Botanique",
        "ligne": "25",
        "timestamp": "2016-12-12T14:36:26+0100"
    },
    {
        "destination": "Jar.-Botanique",
        "ligne": "25",
        "timestamp": "2016-12-12T14:46:26+0100"
    },
    {
        "destination": "Jar.-Botanique",
        "ligne": "25",
        "timestamp": "2016-12-12T14:56:26+0100"
    },
    {
        "destination": "Jar.-Botanique",
        "ligne": "25",
        "timestamp": "2016-12-12T15:06:26+0100"
    },
    {
        "destination": "Jar.-Botanique",
        "ligne": "25",
        "timestamp": "2016-12-12T15:16:26+0100"
    },
    {
        "destination": "Jar.-Botanique",
        "ligne": "25",
        "timestamp": "2016-12-12T15:26:26+0100"
    },
    {
        "destination": "Jar.-Botanique",
        "ligne": "25",
        "timestamp": "2016-12-12T15:36:26+0100"
    },
    {
        "destination": "Jar.-Botanique",
        "ligne": "25",
        "timestamp": "2016-12-12T15:46:26+0100"
    },
    {
        "destination": "Jar.-Botanique",
        "ligne": "25",
        "timestamp": "2016-12-12T15:56:26+0100"
    },
    {
        "destination": "Jar.-Botanique",
        "ligne": "25",
        "timestamp": "2016-12-12T16:06:26+0100"
    },
    {
        "destination": "Jar.-Botanique",
        "ligne": "25",
        "timestamp": "2016-12-12T16:17:26+0100"
    },
    {
        "destination": "Jar.-Botanique",
        "ligne": "25",
        "timestamp": "2016-12-12T16:27:26+0100"
    },
    {
        "destination": "Jar.-Botanique",
        "ligne": "25",
        "timestamp": "2016-12-12T16:37:26+0100"
    },
    {
        "destination": "Jar.-Botanique",
        "ligne": "25",
        "timestamp": "2016-12-12T16:45:26+0100"
    },
    {
        "destination": "Jar.-Botanique",
        "ligne": "25",
        "timestamp": "2016-12-12T16:52:26+0100"
    },
    {
        "destination": "Jar.-Botanique",
        "ligne": "25",
        "timestamp": "2016-12-12T17:00:26+0100"
    },
    {
        "destination": "Jar.-Botanique",
        "ligne": "25",
        "timestamp": "2016-12-12T17:07:26+0100"
    },
    {
        "destination": "Jar.-Botanique",
        "ligne": "25",
        "timestamp": "2016-12-12T17:15:26+0100"
    },
    {
        "destination": "Jar.-Botanique",
        "ligne": "25",
        "timestamp": "2016-12-12T17:23:26+0100"
    },
    {
        "destination": "Jar.-Botanique",
        "ligne": "25",
        "timestamp": "2016-12-12T17:31:26+0100"
    },
    {
        "destination": "Jar.-Botanique",
        "ligne": "25",
        "timestamp": "2016-12-12T17:38:26+0100"
    },
    {
        "destination": "Jar.-Botanique",
        "ligne": "25",
        "timestamp": "2016-12-12T17:46:26+0100"
    },
    {
        "destination": "Jar.-Botanique",
        "ligne": "25",
        "timestamp": "2016-12-12T17:53:26+0100"
    },
    {
        "destination": "Jar.-Botanique",
        "ligne": "25",
        "timestamp": "2016-12-12T18:01:26+0100"
    },
    {
        "destination": "Jar.-Botanique",
        "ligne": "25",
        "timestamp": "2016-12-12T18:09:26+0100"
    },
    {
        "destination": "Jar.-Botanique",
        "ligne": "25",
        "timestamp": "2016-12-12T18:16:26+0100"
    },
    {
        "destination": "Jar.-Botanique",
        "ligne": "25",
        "timestamp": "2016-12-12T18:24:26+0100"
    },
    {
        "destination": "Jar.-Botanique",
        "ligne": "25",
        "timestamp": "2016-12-12T18:31:26+0100"
    },
    {
        "destination": "Jar.-Botanique",
        "ligne": "25",
        "timestamp": "2016-12-12T18:39:26+0100"
    },
    {
        "destination": "Jar.-Botanique",
        "ligne": "25",
        "timestamp": "2016-12-12T18:46:26+0100"
    },
    {
        "destination": "Jar.-Botanique",
        "ligne": "25",
        "timestamp": "2016-12-12T18:54:26+0100"
    },
    {
        "destination": "Jar.-Botanique",
        "ligne": "25",
        "timestamp": "2016-12-12T19:01:26+0100"
    },
    {
        "destination": "Jar.-Botanique",
        "ligne": "25",
        "timestamp": "2016-12-12T19:08:26+0100"
    },
    {
        "destination": "Jar.-Botanique",
        "ligne": "25",
        "timestamp": "2016-12-12T19:16:26+0100"
    },
    {
        "destination": "Jar.-Botanique",
        "ligne": "25",
        "timestamp": "2016-12-12T19:24:26+0100"
    },
    {
        "destination": "Jar.-Botanique",
        "ligne": "25",
        "timestamp": "2016-12-12T19:31:26+0100"
    },
    {
        "destination": "Jar.-Botanique",
        "ligne": "25",
        "timestamp": "2016-12-12T19:39:26+0100"
    },
    {
        "destination": "Jar.-Botanique",
        "ligne": "25",
        "timestamp": "2016-12-12T19:46:26+0100"
    },
    {
        "destination": "Jar.-Botanique",
        "ligne": "25",
        "timestamp": "2016-12-12T19:56:26+0100"
    },
    {
        "destination": "Jar.-Botanique",
        "ligne": "25",
        "timestamp": "2016-12-12T20:05:26+0100"
    },
    {
        "destination": "Jar.-Botanique",
        "ligne": "25",
        "timestamp": "2016-12-12T20:15:26+0100"
    },
    {
        "destination": "Jar.-Botanique",
        "ligne": "25",
        "timestamp": "2016-12-12T20:26:26+0100"
    },
    {
        "destination": "Jar.-Botanique",
        "ligne": "25",
        "timestamp": "2016-12-12T20:41:26+0100"
    },
    {
        "destination": "Jar.-Botanique",
        "ligne": "25",
        "timestamp": "2016-12-12T20:56:26+0100"
    },
    {
        "destination": "Jar.-Botanique",
        "ligne": "25",
        "timestamp": "2016-12-12T21:10:26+0100"
    },
    {
        "destination": "Jar.-Botanique",
        "ligne": "25",
        "timestamp": "2016-12-12T21:25:26+0100"
    },
    {
        "destination": "Jar.-Botanique",
        "ligne": "25",
        "timestamp": "2016-12-12T21:41:26+0100"
    },
    {
        "destination": "Jar.-Botanique",
        "ligne": "25",
        "timestamp": "2016-12-12T22:01:26+0100"
    },
    {
        "destination": "Jar.-Botanique",
        "ligne": "25",
        "timestamp": "2016-12-12T22:21:26+0100"
    },
    {
        "destination": "Jar.-Botanique",
        "ligne": "25",
        "timestamp": "2016-12-12T22:42:26+0100"
    },
    {
        "destination": "Jar.-Botanique",
        "ligne": "25",
        "timestamp": "2016-12-12T23:02:26+0100"
    },
    {
        "destination": "Jar.-Botanique",
        "ligne": "25",
        "timestamp": "2016-12-12T23:22:26+0100"
    },
    {
        "destination": "Jar.-Botanique",
        "ligne": "25",
        "timestamp": "2016-12-12T23:42:26+0100"
    },
    {
        "destination": "Jar.-Botanique",
        "ligne": "25",
        "timestamp": "2016-12-13T00:01:26+0100"
    },
    {
        "destination": "Jar.-Botanique",
        "ligne": "25",
        "timestamp": "2016-12-13T00:21:26+0100"
    },
    {
        "destination": "Thônex-Vallard",
        "ligne": "25",
        "timestamp": "2016-12-12T04:57:27+0100"
    },
    {
        "destination": "Thônex-Vallard",
        "ligne": "25",
        "timestamp": "2016-12-12T05:16:27+0100"
    },
    {
        "destination": "Thônex-Vallard",
        "ligne": "25",
        "timestamp": "2016-12-12T05:36:27+0100"
    },
    {
        "destination": "Thônex-Vallard",
        "ligne": "25",
        "timestamp": "2016-12-12T05:56:27+0100"
    },
    {
        "destination": "Thônex-Vallard",
        "ligne": "25",
        "timestamp": "2016-12-12T06:14:27+0100"
    },
    {
        "destination": "Thônex-Vallard",
        "ligne": "25",
        "timestamp": "2016-12-12T06:29:27+0100"
    },
    {
        "destination": "Thônex-Vallard",
        "ligne": "25",
        "timestamp": "2016-12-12T06:45:27+0100"
    },
    {
        "destination": "Thônex-Vallard",
        "ligne": "25",
        "timestamp": "2016-12-12T06:58:27+0100"
    },
    {
        "destination": "Thônex-Vallard",
        "ligne": "25",
        "timestamp": "2016-12-12T07:07:27+0100"
    },
    {
        "destination": "Thônex-Vallard",
        "ligne": "25",
        "timestamp": "2016-12-12T07:14:27+0100"
    },
    {
        "destination": "Thônex-Vallard",
        "ligne": "25",
        "timestamp": "2016-12-12T07:22:27+0100"
    },
    {
        "destination": "Thônex-Vallard",
        "ligne": "25",
        "timestamp": "2016-12-12T07:29:27+0100"
    },
    {
        "destination": "Thônex-Vallard",
        "ligne": "25",
        "timestamp": "2016-12-12T07:38:27+0100"
    },
    {
        "destination": "Thônex-Vallard",
        "ligne": "25",
        "timestamp": "2016-12-12T07:46:27+0100"
    },
    {
        "destination": "Thônex-Vallard",
        "ligne": "25",
        "timestamp": "2016-12-12T07:53:27+0100"
    },
    {
        "destination": "Thônex-Vallard",
        "ligne": "25",
        "timestamp": "2016-12-12T08:01:27+0100"
    },
    {
        "destination": "Thônex-Vallard",
        "ligne": "25",
        "timestamp": "2016-12-12T08:08:27+0100"
    },
    {
        "destination": "Thônex-Vallard",
        "ligne": "25",
        "timestamp": "2016-12-12T08:16:27+0100"
    },
    {
        "destination": "Thônex-Vallard",
        "ligne": "25",
        "timestamp": "2016-12-12T08:23:27+0100"
    },
    {
        "destination": "Thônex-Vallard",
        "ligne": "25",
        "timestamp": "2016-12-12T08:31:27+0100"
    },
    {
        "destination": "Thônex-Vallard",
        "ligne": "25",
        "timestamp": "2016-12-12T08:38:27+0100"
    },
    {
        "destination": "Thônex-Vallard",
        "ligne": "25",
        "timestamp": "2016-12-12T08:46:27+0100"
    },
    {
        "destination": "Thônex-Vallard",
        "ligne": "25",
        "timestamp": "2016-12-12T08:53:27+0100"
    },
    {
        "destination": "Thônex-Vallard",
        "ligne": "25",
        "timestamp": "2016-12-12T09:00:27+0100"
    },
    {
        "destination": "Thônex-Vallard",
        "ligne": "25",
        "timestamp": "2016-12-12T09:08:27+0100"
    },
    {
        "destination": "Thônex-Vallard",
        "ligne": "25",
        "timestamp": "2016-12-12T09:17:27+0100"
    },
    {
        "destination": "Thônex-Vallard",
        "ligne": "25",
        "timestamp": "2016-12-12T09:27:27+0100"
    },
    {
        "destination": "Thônex-Vallard",
        "ligne": "25",
        "timestamp": "2016-12-12T09:37:27+0100"
    },
    {
        "destination": "Thônex-Vallard",
        "ligne": "25",
        "timestamp": "2016-12-12T09:47:27+0100"
    },
    {
        "destination": "Thônex-Vallard",
        "ligne": "25",
        "timestamp": "2016-12-12T09:57:27+0100"
    },
    {
        "destination": "Thônex-Vallard",
        "ligne": "25",
        "timestamp": "2016-12-12T10:07:27+0100"
    },
    {
        "destination": "Thônex-Vallard",
        "ligne": "25",
        "timestamp": "2016-12-12T10:17:27+0100"
    },
    {
        "destination": "Thônex-Vallard",
        "ligne": "25",
        "timestamp": "2016-12-12T10:27:27+0100"
    },
    {
        "destination": "Thônex-Vallard",
        "ligne": "25",
        "timestamp": "2016-12-12T10:37:27+0100"
    },
    {
        "destination": "Thônex-Vallard",
        "ligne": "25",
        "timestamp": "2016-12-12T10:47:27+0100"
    },
    {
        "destination": "Thônex-Vallard",
        "ligne": "25",
        "timestamp": "2016-12-12T10:57:27+0100"
    },
    {
        "destination": "Thônex-Vallard",
        "ligne": "25",
        "timestamp": "2016-12-12T11:07:27+0100"
    },
    {
        "destination": "Thônex-Vallard",
        "ligne": "25",
        "timestamp": "2016-12-12T11:17:27+0100"
    },
    {
        "destination": "Thônex-Vallard",
        "ligne": "25",
        "timestamp": "2016-12-12T11:27:27+0100"
    },
    {
        "destination": "Thônex-Vallard",
        "ligne": "25",
        "timestamp": "2016-12-12T11:37:27+0100"
    },
    {
        "destination": "Thônex-Vallard",
        "ligne": "25",
        "timestamp": "2016-12-12T11:47:27+0100"
    },
    {
        "destination": "Thônex-Vallard",
        "ligne": "25",
        "timestamp": "2016-12-12T11:57:27+0100"
    },
    {
        "destination": "Thônex-Vallard",
        "ligne": "25",
        "timestamp": "2016-12-12T12:07:27+0100"
    },
    {
        "destination": "Thônex-Vallard",
        "ligne": "25",
        "timestamp": "2016-12-12T12:17:27+0100"
    },
    {
        "destination": "Thônex-Vallard",
        "ligne": "25",
        "timestamp": "2016-12-12T12:27:27+0100"
    },
    {
        "destination": "Thônex-Vallard",
        "ligne": "25",
        "timestamp": "2016-12-12T12:37:27+0100"
    },
    {
        "destination": "Thônex-Vallard",
        "ligne": "25",
        "timestamp": "2016-12-12T12:47:27+0100"
    },
    {
        "destination": "Thônex-Vallard",
        "ligne": "25",
        "timestamp": "2016-12-12T12:57:27+0100"
    },
    {
        "destination": "Thônex-Vallard",
        "ligne": "25",
        "timestamp": "2016-12-12T13:07:27+0100"
    },
    {
        "destination": "Thônex-Vallard",
        "ligne": "25",
        "timestamp": "2016-12-12T13:17:27+0100"
    },
    {
        "destination": "Thônex-Vallard",
        "ligne": "25",
        "timestamp": "2016-12-12T13:27:27+0100"
    },
    {
        "destination": "Thônex-Vallard",
        "ligne": "25",
        "timestamp": "2016-12-12T13:37:27+0100"
    },
    {
        "destination": "Thônex-Vallard",
        "ligne": "25",
        "timestamp": "2016-12-12T13:47:27+0100"
    },
    {
        "destination": "Thônex-Vallard",
        "ligne": "25",
        "timestamp": "2016-12-12T13:57:27+0100"
    },
    {
        "destination": "Thônex-Vallard",
        "ligne": "25",
        "timestamp": "2016-12-12T14:07:27+0100"
    },
    {
        "destination": "Thônex-Vallard",
        "ligne": "25",
        "timestamp": "2016-12-12T14:17:27+0100"
    },
    {
        "destination": "Thônex-Vallard",
        "ligne": "25",
        "timestamp": "2016-12-12T14:27:27+0100"
    },
    {
        "destination": "Thônex-Vallard",
        "ligne": "25",
        "timestamp": "2016-12-12T14:37:27+0100"
    },
    {
        "destination": "Thônex-Vallard",
        "ligne": "25",
        "timestamp": "2016-12-12T14:47:27+0100"
    },
    {
        "destination": "Thônex-Vallard",
        "ligne": "25",
        "timestamp": "2016-12-12T14:57:27+0100"
    },
    {
        "destination": "Thônex-Vallard",
        "ligne": "25",
        "timestamp": "2016-12-12T15:07:27+0100"
    },
    {
        "destination": "Thônex-Vallard",
        "ligne": "25",
        "timestamp": "2016-12-12T15:17:27+0100"
    },
    {
        "destination": "Thônex-Vallard",
        "ligne": "25",
        "timestamp": "2016-12-12T15:27:27+0100"
    },
    {
        "destination": "Thônex-Vallard",
        "ligne": "25",
        "timestamp": "2016-12-12T15:37:27+0100"
    },
    {
        "destination": "Thônex-Vallard",
        "ligne": "25",
        "timestamp": "2016-12-12T15:47:27+0100"
    },
    {
        "destination": "Thônex-Vallard",
        "ligne": "25",
        "timestamp": "2016-12-12T15:54:27+0100"
    },
    {
        "destination": "Thônex-Vallard",
        "ligne": "25",
        "timestamp": "2016-12-12T16:02:27+0100"
    },
    {
        "destination": "Thônex-Vallard",
        "ligne": "25",
        "timestamp": "2016-12-12T16:09:27+0100"
    },
    {
        "destination": "Thônex-Vallard",
        "ligne": "25",
        "timestamp": "2016-12-12T16:17:27+0100"
    },
    {
        "destination": "Thônex-Vallard",
        "ligne": "25",
        "timestamp": "2016-12-12T16:26:27+0100"
    },
    {
        "destination": "Thônex-Vallard",
        "ligne": "25",
        "timestamp": "2016-12-12T16:33:27+0100"
    },
    {
        "destination": "Thônex-Vallard",
        "ligne": "25",
        "timestamp": "2016-12-12T16:40:27+0100"
    },
    {
        "destination": "Thônex-Vallard",
        "ligne": "25",
        "timestamp": "2016-12-12T16:48:27+0100"
    },
    {
        "destination": "Thônex-Vallard",
        "ligne": "25",
        "timestamp": "2016-12-12T16:55:27+0100"
    },
    {
        "destination": "Thônex-Vallard",
        "ligne": "25",
        "timestamp": "2016-12-12T17:04:27+0100"
    },
    {
        "destination": "Thônex-Vallard",
        "ligne": "25",
        "timestamp": "2016-12-12T17:11:27+0100"
    },
    {
        "destination": "Thônex-Vallard",
        "ligne": "25",
        "timestamp": "2016-12-12T17:19:27+0100"
    },
    {
        "destination": "Thônex-Vallard",
        "ligne": "25",
        "timestamp": "2016-12-12T17:26:27+0100"
    },
    {
        "destination": "Thônex-Vallard",
        "ligne": "25",
        "timestamp": "2016-12-12T17:34:27+0100"
    },
    {
        "destination": "Thônex-Vallard",
        "ligne": "25",
        "timestamp": "2016-12-12T17:41:27+0100"
    },
    {
        "destination": "Thônex-Vallard",
        "ligne": "25",
        "timestamp": "2016-12-12T17:49:27+0100"
    },
    {
        "destination": "Thônex-Vallard",
        "ligne": "25",
        "timestamp": "2016-12-12T17:56:27+0100"
    },
    {
        "destination": "Thônex-Vallard",
        "ligne": "25",
        "timestamp": "2016-12-12T18:04:27+0100"
    },
    {
        "destination": "Thônex-Vallard",
        "ligne": "25",
        "timestamp": "2016-12-12T18:12:27+0100"
    },
    {
        "destination": "Thônex-Vallard",
        "ligne": "25",
        "timestamp": "2016-12-12T18:19:27+0100"
    },
    {
        "destination": "Thônex-Vallard",
        "ligne": "25",
        "timestamp": "2016-12-12T18:27:27+0100"
    },
    {
        "destination": "Thônex-Vallard",
        "ligne": "25",
        "timestamp": "2016-12-12T18:34:27+0100"
    },
    {
        "destination": "Thônex-Vallard",
        "ligne": "25",
        "timestamp": "2016-12-12T18:42:27+0100"
    },
    {
        "destination": "Thônex-Vallard",
        "ligne": "25",
        "timestamp": "2016-12-12T18:49:27+0100"
    },
    {
        "destination": "Thônex-Vallard",
        "ligne": "25",
        "timestamp": "2016-12-12T18:57:27+0100"
    },
    {
        "destination": "Thônex-Vallard",
        "ligne": "25",
        "timestamp": "2016-12-12T19:04:27+0100"
    },
    {
        "destination": "Thônex-Vallard",
        "ligne": "25",
        "timestamp": "2016-12-12T19:14:27+0100"
    },
    {
        "destination": "Thônex-Vallard",
        "ligne": "25",
        "timestamp": "2016-12-12T19:23:27+0100"
    },
    {
        "destination": "Thônex-Vallard",
        "ligne": "25",
        "timestamp": "2016-12-12T19:33:27+0100"
    },
    {
        "destination": "Thônex-Vallard",
        "ligne": "25",
        "timestamp": "2016-12-12T19:43:27+0100"
    },
    {
        "destination": "Thônex-Vallard",
        "ligne": "25",
        "timestamp": "2016-12-12T19:55:27+0100"
    },
    {
        "destination": "Thônex-Vallard",
        "ligne": "25",
        "timestamp": "2016-12-12T20:09:27+0100"
    },
    {
        "destination": "Thônex-Vallard",
        "ligne": "25",
        "timestamp": "2016-12-12T20:24:27+0100"
    },
    {
        "destination": "Thônex-Vallard",
        "ligne": "25",
        "timestamp": "2016-12-12T20:39:27+0100"
    },
    {
        "destination": "Thônex-Vallard",
        "ligne": "25",
        "timestamp": "2016-12-12T20:53:27+0100"
    },
    {
        "destination": "Thônex-Vallard",
        "ligne": "25",
        "timestamp": "2016-12-12T21:09:27+0100"
    },
    {
        "destination": "Thônex-Vallard",
        "ligne": "25",
        "timestamp": "2016-12-12T21:29:27+0100"
    },
    {
        "destination": "Thônex-Vallard",
        "ligne": "25",
        "timestamp": "2016-12-12T21:49:27+0100"
    },
    {
        "destination": "Thônex-Vallard",
        "ligne": "25",
        "timestamp": "2016-12-12T22:09:27+0100"
    },
    {
        "destination": "Thônex-Vallard",
        "ligne": "25",
        "timestamp": "2016-12-12T22:29:27+0100"
    },
    {
        "destination": "Thônex-Vallard",
        "ligne": "25",
        "timestamp": "2016-12-12T22:48:27+0100"
    },
    {
        "destination": "Thônex-Vallard",
        "ligne": "25",
        "timestamp": "2016-12-12T23:08:27+0100"
    },
    {
        "destination": "Thônex-Vallard",
        "ligne": "25",
        "timestamp": "2016-12-12T23:28:27+0100"
    },
    {
        "destination": "Thônex-Vallard",
        "ligne": "25",
        "timestamp": "2016-12-12T23:48:27+0100"
    },
    {
        "destination": "Thônex-Vallard",
        "ligne": "25",
        "timestamp": "2016-12-13T00:08:27+0100"
    }
]