[
    {
        "destination": "Gy",
        "ligne": "A",
        "timestamp": "2016-02-27T11:06:27+0100"
    },
    {
        "destination": "Gy",
        "ligne": "A",
        "timestamp": "2016-02-27T11:45:27+0100"
    },
    {
        "destination": "Gy",
        "ligne": "A",
        "timestamp": "2016-02-27T12:15:27+0100"
    },
    {
        "destination": "Gy",
        "ligne": "A",
        "timestamp": "2016-02-27T12:45:27+0100"
    },
    {
        "destination": "Gy",
        "ligne": "A",
        "timestamp": "2016-02-27T13:15:27+0100"
    },
    {
        "destination": "Gy",
        "ligne": "A",
        "timestamp": "2016-02-27T13:45:27+0100"
    },
    {
        "destination": "Gy",
        "ligne": "A",
        "timestamp": "2016-02-27T14:15:27+0100"
    },
    {
        "destination": "Gy",
        "ligne": "A",
        "timestamp": "2016-02-27T14:45:27+0100"
    },
    {
        "destination": "Gy",
        "ligne": "A",
        "timestamp": "2016-02-27T15:15:27+0100"
    },
    {
        "destination": "Gy",
        "ligne": "A",
        "timestamp": "2016-02-27T15:46:27+0100"
    },
    {
        "destination": "Gy",
        "ligne": "A",
        "timestamp": "2016-02-27T16:16:27+0100"
    },
    {
        "destination": "Gy",
        "ligne": "A",
        "timestamp": "2016-02-27T16:46:27+0100"
    },
    {
        "destination": "Gy",
        "ligne": "A",
        "timestamp": "2016-02-27T17:16:27+0100"
    },
    {
        "destination": "Gy",
        "ligne": "A",
        "timestamp": "2016-02-27T17:47:27+0100"
    },
    {
        "destination": "Gy",
        "ligne": "A",
        "timestamp": "2016-02-27T18:17:27+0100"
    },
    {
        "destination": "Gy",
        "ligne": "A",
        "timestamp": "2016-02-27T18:47:27+0100"
    },
    {
        "destination": "Gy",
        "ligne": "A",
        "timestamp": "2016-02-27T20:05:27+0100"
    },
    {
        "destination": "Gy",
        "ligne": "A",
        "timestamp": "2016-02-27T21:05:27+0100"
    },
    {
        "destination": "Gy",
        "ligne": "A",
        "timestamp": "2016-02-27T22:04:27+0100"
    },
    {
        "destination": "Gy",
        "ligne": "A",
        "timestamp": "2016-02-27T23:04:27+0100"
    },
    {
        "destination": "Gy",
        "ligne": "A",
        "timestamp": "2016-02-28T00:07:27+0100"
    },
    {
        "destination": "Gy - Corsinge",
        "ligne": "A",
        "timestamp": "2016-02-27T19:26:27+0100"
    },
    {
        "destination": "Gy - Corsinge",
        "ligne": "A",
        "timestamp": "2016-02-27T19:33:27+0100"
    },
    {
        "destination": "Rive",
        "ligne": "A",
        "timestamp": "2016-02-27T10:31:27+0100"
    },
    {
        "destination": "Rive",
        "ligne": "A",
        "timestamp": "2016-02-27T11:17:27+0100"
    },
    {
        "destination": "Rive",
        "ligne": "A",
        "timestamp": "2016-02-27T12:02:27+0100"
    },
    {
        "destination": "Rive",
        "ligne": "A",
        "timestamp": "2016-02-27T12:32:27+0100"
    },
    {
        "destination": "Rive",
        "ligne": "A",
        "timestamp": "2016-02-27T13:03:27+0100"
    },
    {
        "destination": "Rive",
        "ligne": "A",
        "timestamp": "2016-02-27T13:30:27+0100"
    },
    {
        "destination": "Rive",
        "ligne": "A",
        "timestamp": "2016-02-27T14:03:27+0100"
    },
    {
        "destination": "Rive",
        "ligne": "A",
        "timestamp": "2016-02-27T14:33:27+0100"
    },
    {
        "destination": "Rive",
        "ligne": "A",
        "timestamp": "2016-02-27T15:03:27+0100"
    },
    {
        "destination": "Rive",
        "ligne": "A",
        "timestamp": "2016-02-27T15:32:27+0100"
    },
    {
        "destination": "Rive",
        "ligne": "A",
        "timestamp": "2016-02-27T16:02:27+0100"
    },
    {
        "destination": "Rive",
        "ligne": "A",
        "timestamp": "2016-02-27T16:32:27+0100"
    },
    {
        "destination": "Rive",
        "ligne": "A",
        "timestamp": "2016-02-27T17:02:27+0100"
    },
    {
        "destination": "Rive",
        "ligne": "A",
        "timestamp": "2016-02-27T17:32:27+0100"
    },
    {
        "destination": "Rive",
        "ligne": "A",
        "timestamp": "2016-02-27T18:02:27+0100"
    },
    {
        "destination": "Rive",
        "ligne": "A",
        "timestamp": "2016-02-27T18:32:27+0100"
    },
    {
        "destination": "Rive",
        "ligne": "A",
        "timestamp": "2016-02-27T19:02:27+0100"
    },
    {
        "destination": "Rive",
        "ligne": "A",
        "timestamp": "2016-02-27T20:37:27+0100"
    },
    {
        "destination": "Rive",
        "ligne": "A",
        "timestamp": "2016-02-27T21:37:27+0100"
    },
    {
        "destination": "Rive",
        "ligne": "A",
        "timestamp": "2016-02-27T22:37:27+0100"
    },
    {
        "destination": "Rive",
        "ligne": "A",
        "timestamp": "2016-02-27T23:37:27+0100"
    },
    {
        "destination": "Rive",
        "ligne": "A",
        "timestamp": "2016-02-28T00:37:27+0100"
    }
]