[
    {
        "destination": "Tours-de-Carouge",
        "ligne": "45",
        "timestamp": "2017-02-26T07:08:27+0100"
    },
    {
        "destination": "Tours-de-Carouge",
        "ligne": "45",
        "timestamp": "2017-02-26T08:08:27+0100"
    },
    {
        "destination": "Tours-de-Carouge",
        "ligne": "45",
        "timestamp": "2017-02-26T09:08:27+0100"
    },
    {
        "destination": "Tours-de-Carouge",
        "ligne": "45",
        "timestamp": "2017-02-26T10:08:27+0100"
    },
    {
        "destination": "Tours-de-Carouge",
        "ligne": "45",
        "timestamp": "2017-02-26T11:08:27+0100"
    },
    {
        "destination": "Tours-de-Carouge",
        "ligne": "45",
        "timestamp": "2017-02-26T12:08:27+0100"
    },
    {
        "destination": "Tours-de-Carouge",
        "ligne": "45",
        "timestamp": "2017-02-26T13:08:27+0100"
    },
    {
        "destination": "Tours-de-Carouge",
        "ligne": "45",
        "timestamp": "2017-02-26T14:08:27+0100"
    },
    {
        "destination": "Tours-de-Carouge",
        "ligne": "45",
        "timestamp": "2017-02-26T15:08:27+0100"
    },
    {
        "destination": "Tours-de-Carouge",
        "ligne": "45",
        "timestamp": "2017-02-26T16:08:27+0100"
    },
    {
        "destination": "Tours-de-Carouge",
        "ligne": "45",
        "timestamp": "2017-02-26T17:08:27+0100"
    },
    {
        "destination": "Tours-de-Carouge",
        "ligne": "45",
        "timestamp": "2017-02-26T18:08:27+0100"
    },
    {
        "destination": "Tours-de-Carouge",
        "ligne": "45",
        "timestamp": "2017-02-26T19:08:27+0100"
    },
    {
        "destination": "Tours-de-Carouge",
        "ligne": "45",
        "timestamp": "2017-02-26T20:08:27+0100"
    },
    {
        "destination": "Tours-de-Carouge",
        "ligne": "45",
        "timestamp": "2017-02-26T21:08:27+0100"
    },
    {
        "destination": "Tours-de-Carouge",
        "ligne": "45",
        "timestamp": "2017-02-26T22:08:27+0100"
    },
    {
        "destination": "Tours-de-Carouge",
        "ligne": "45",
        "timestamp": "2017-02-26T23:09:27+0100"
    },
    {
        "destination": "Tours-de-Carouge",
        "ligne": "45",
        "timestamp": "2017-02-27T00:08:27+0100"
    },
    {
        "destination": "Troinex-Ville",
        "ligne": "45",
        "timestamp": "2017-02-26T06:55:28+0100"
    },
    {
        "destination": "Troinex-Ville",
        "ligne": "45",
        "timestamp": "2017-02-26T07:55:28+0100"
    },
    {
        "destination": "Troinex-Ville",
        "ligne": "45",
        "timestamp": "2017-02-26T08:55:28+0100"
    },
    {
        "destination": "Troinex-Ville",
        "ligne": "45",
        "timestamp": "2017-02-26T09:56:28+0100"
    },
    {
        "destination": "Troinex-Ville",
        "ligne": "45",
        "timestamp": "2017-02-26T10:56:28+0100"
    },
    {
        "destination": "Troinex-Ville",
        "ligne": "45",
        "timestamp": "2017-02-26T11:57:28+0100"
    },
    {
        "destination": "Troinex-Ville",
        "ligne": "45",
        "timestamp": "2017-02-26T12:56:28+0100"
    },
    {
        "destination": "Troinex-Ville",
        "ligne": "45",
        "timestamp": "2017-02-26T13:56:28+0100"
    },
    {
        "destination": "Troinex-Ville",
        "ligne": "45",
        "timestamp": "2017-02-26T14:56:28+0100"
    },
    {
        "destination": "Troinex-Ville",
        "ligne": "45",
        "timestamp": "2017-02-26T15:56:28+0100"
    },
    {
        "destination": "Troinex-Ville",
        "ligne": "45",
        "timestamp": "2017-02-26T16:56:28+0100"
    },
    {
        "destination": "Troinex-Ville",
        "ligne": "45",
        "timestamp": "2017-02-26T17:56:28+0100"
    },
    {
        "destination": "Troinex-Ville",
        "ligne": "45",
        "timestamp": "2017-02-26T18:56:28+0100"
    },
    {
        "destination": "Troinex-Ville",
        "ligne": "45",
        "timestamp": "2017-02-26T19:56:28+0100"
    },
    {
        "destination": "Troinex-Ville",
        "ligne": "45",
        "timestamp": "2017-02-26T20:55:28+0100"
    },
    {
        "destination": "Troinex-Ville",
        "ligne": "45",
        "timestamp": "2017-02-26T21:55:28+0100"
    },
    {
        "destination": "Troinex-Ville",
        "ligne": "45",
        "timestamp": "2017-02-26T22:56:28+0100"
    },
    {
        "destination": "Troinex-Ville",
        "ligne": "45",
        "timestamp": "2017-02-26T23:55:28+0100"
    }
]